celery_service_task/MessageMetadata.py
celery_service_task/__init__.py
celery_service_task/task.py
celery_service_task-0.9.0.dist-info/METADATA
celery_service_task-0.9.0.dist-info/WHEEL
celery_service_task-0.9.0.dist-info/top_level.txt
celery_service_task-0.9.0.dist-info/RECORD
