Metadata-Version: 2.1
Name: celery-service-task
Version: 0.9.0
Summary: UNKNOWN
Home-page: UNKNOWN
Author: di-dip-unistra
Author-email: di-dip@unistra.fr
Maintainer: di-dip-unistra
Maintainer-email: di-dip@unistra.fr
License: PSF
Keywords: celery,AMQP,unistra,Université de Strasbourg,serivce,skinos
Platform: UNKNOWN
